Workbook

Sheet Tier 1 Equipment Costs
A1: Tier 1 Equipment Costs — Sticker Side Hustle
A2: Prices checked July–Sep 2026 (GBP; Explore 5, ET-3950 and laminator re-checked 19 Sep 2026). Blue = editable input. Black = calculated.
A4: Item | B4: Low (£) | C4: Category | D4: Notes
A5: Epson EcoTank ET-3950 (pigment-ink printer, current gen) | B5: 370 | C5: Core | D5: Pigment black ink for waterproof prints. Epson UK £369.99 (before a £50 cashback offer), checked 19 Sep 2026
A6: Printable vinyl sticker paper (starter pack) | B6: 0 | C6: Core | D6: A4 waterproof printable vinyl | E6: moved to r&d
A7: Self-adhesive laminate sheets + squeegee | B7: 0 | C7: Core | D7: Cold lamination sheets, feeds through laminator | E7: moved to r&d
A8: Manual cold roll laminator (Stickiply 14", 35cm) — ordered | B8: 115 | C8: Core | D8: Ordered Sep 2026; Stickiply list price £115 checked 19 Sep 2026. Promoted from optional — removes bubble/wrinkle risk vs hand-applying | E8: Stickiply
A9: Backup Epson 101/102 ink bottles | B9: 0 | C9: Core | D9: UK naming (not '502' — that's US)
A10: A4 guillotine/paper trimmer (metal-base) | B10: 38 | C10: Core | D10: Trims the kiss-cut sheet into separate backed stickers (and thank-you cards to A6). Cricut cut-only now does the cutting — see Equipment Guide
A11: Cricut Explore 5 — Ultimate Bundle (cutting machine) | B11: 330 | C11: Core | D11: Paid £330 (Sep 2026). Cut-only for all bin sticker sizes — see Equipment Guide
A12: CORE SUBTOTAL (required to start) | B12: =SUM(B5:B11) -> 853
A14: ON HOLD — decide after test cuts (not in core total)
A15: Corner rounder punch (3-in-1) | B15: 7 | C15: On hold | D15: Likely superseded: the Cricut cuts the rounded corners
A16: Slice 00200/00100 safety cutter | B16: 5 | C16: On hold | D16: May still help with a peel-start once the backing is trimmed flush — decide after test cuts
A17: Self-Healing Cutting Mat (A4) | B17: 4 | C17: On hold | D17: Was for the Slice workflow
A18: ON HOLD SUBTOTAL | B18: =SUM(B15:B17) -> 16
A20: Optional Equipment (not required to launch)
A21: Item | B21: Low (£) | C21: Category | D21: Notes
A22: Cricut Access Standard subscription (annual) | B22: 96 | C22: Optional | D22: ~$9.99/mo; not needed for custom text/number designs — free tier covers your use case
A23: OPTIONAL SUBTOTAL | B23: =SUM(B22:B22) -> 96
A24: TOTAL — Core + Cricut Access (recommended launch budget) | B24: =B12+B22 -> 949
A26: Removed Sep 2026: the Cricut Essential Bundle and 6-ct sticker set alternatives (the Ultimate Bundle was bought; the 20-ct set is in the R&D list below). On-hold tools are excluded from all totals until decided.
A29: R&D / Testing Materials (one-off, sunk cost — see Bin-Sticker-Material-Test-Plan.md)
A30: Item | B30: Low (£) | C30: Category | D30: Notes | E30: count
A31: Matte Self-Adhesive Laminate | Pro UV × 1 | B31: 13 | E31: 25 | F31: =B31/E31 -> 0.52 | G31: Stickiply
A32: Printable Vinyl Sticker Paper | Clear (A4) × 1 | B32: 8 | C32: R&D | D32: One-off purchase of all 4 packaging candidates for side-by-side comparison. See Bin-Sticker-Shipping-Plan.md 'Testing shopping list' (~£33–35 total as pinned there — update once actually spent). | E32: 10 | F32: =B32/E32 -> 0.8 | G32: Stickiply
A33: Printable Vinyl Sticker Paper | Glossy (A4) × 1 | B33: 5.85 | C33: R&D | D33: 2nd Class postage for the 4 test parcels in Test 6. See Bin-Sticker-Shipping-Plan.md. | E33: 10 | F33: =B33/E33 -> 0.585 | G33: Stickiply
A34: Brown Kraft Card, A4 Card 250GSM Thick Kraft Card Stock for Cards Making, Scrapbook, Office Printing and Arts or Crafts DIY (25 Sheets) | B34: 6 | E34: 25 | F34: =B34/E34 -> 0.24 | G34: amazon
A35: Double Dragon 50-Pack A6 C6 Manilla Hard Board Backed Envelopes | 162mm x 114mm | 'Please Do Not Bend' Printed | Padded & Tamper-Proof | Self-Seal Closure | B35: 7.37 | E35: 50 | F35: =B35/E35 -> 0.1474 | G35: amazon
A36: White Card, A4 Card 250GSM Thick Card Stock for Cards Making, Scrapbook, Office Printing and Arts or Crafts DIY (25 Sheets) | B36: 6 | E36: 25 | F36: =B36/E36 -> 0.24 | G36: amazon
A37: SmithPackaging A4 Self Adhesive Address Labels, 1 Label Per Sheet, 100 Sheets, 199.6 x 289.1mm, 100 Labels | B37: 9 | E37: 100 | F37: =B37/E37 -> 0.09 | G37: amazon
A38: 40 Sheets of Acid Free Tissue Paper Cool White MG 17gsm Clothing Storage Gift Wrapping Decorative Sketch and Cutting Large Tissue Paper for Art Craft and Packing - 500mm x 750mm | B38: 5 | E38: 40 | F38: =B38/E38 -> 0.125 | G38: amazon
A39: Triplast White Bubble Padded Envelopes - Pick Qty & Size: 10 x 1/A (100x165mm) A6 Envelopes - Large Letter Postal Bags with Bubble Wrap Lining and Peel & Seal Strip for Royal Mail Shipping & Postage | B39: 6.09 | E39: 10 | F39: =B39/E39 -> 0.609 | G39: amazon
A40: AKAR White A6/C6 Large Letter Postal Box - 112x163x20 mm - Letterbox Pip Royal Mail Small Boxes for Posting [Pack of 50] | B40: 10 | E40: 50 | F40: =B40/E40 -> 0.2 | G40: amazon
A41: Printable Waterproof Sticker Set – A4 (20 ct), White | B41: 13 | E41: 20 | F41: =(B41+I41)/E41 -> 0.85 | G41: cricut | H41: Shipping | I41: 4
A42: Printable Waterproof Sticker Set – A4 (20 ct), Transparent | B42: 13 | E42: 20 | F42: =(B42+I42)/E42 -> 0.85 | G42: cricut | H42: Shipping | I42: 4
A43: R&D SUBTOTAL | B43: =SUM(B31:B42) -> 102.31
A45: TOTAL SUNK STARTUP COST (Core Equipment + R&D Materials) | B45: =B12+B43 -> 955.31
A46: Excludes Optional and On-hold items (Cricut Access, corner punch, Slice, mat).
A48: BREAK-EVEN CALCULATOR
A49: Live model. Price and eBay fees come from the 'Ebay costs' sheet, direct costs from the 'Bin Stickers 100x140 4pk' sheet, overhead from 'Recurring Overhead' (active volume scenario). Change those cells and everything here updates.
A51: Sale price per pack, eBay (£) | B51: ='Ebay costs'!B5 -> 5 | D51: Set on the 'Ebay costs' sheet (eBay price £5.00, Oct 2026)
A52: eBay fees per pack incl. ads (£) | B52: ='Ebay costs'!B15 -> 1.392 | D52: FVF + regulatory fee + per-order fee + Promoted Listings ad rate
A53: Direct cost per pack (£) | B53: ='Bin Stickers 100x140 4pk'!B120 -> 2.7336662 | D53: Materials + packaging + postage + address label + thank-you card. Excludes recurring overhead
A54: → Profit per pack before overhead (£) | B54: =B51-B52-B53 -> 0.87433385
A56: Total sunk startup cost (from above) | B56: =B45 -> 955.31
A57: → Packs needed to recover startup cost | B57: =IF(B54>0,B56/B54,"N/A") -> 1092.6147
A58: → Individual stickers to recover startup cost | B58: =IF(ISNUMBER(B57),B57*'Bin Stickers 100x140 4pk'!B7,"N/A") -> 4370.4587
A60: Monthly recurring overhead (£) | B60: ='Recurring Overhead'!B12 -> 83.223333 | D60: Fixed monthly subscriptions incl. virtual office (£250/yr ÷ 12)
A61: → Packs per month needed to cover overhead | B61: =IF(B54>0,B60/B54,"N/A") -> 95.184847
A62: → Stickers per month needed to cover overhead | B62: =IF(ISNUMBER(B61),B61*'Bin Stickers 100x140 4pk'!B7,"N/A") -> 380.73939
A63: Active overhead scenario volume (stickers/month) | B63: ='Recurring Overhead'!B33 -> 10 | D63: From 'Recurring Overhead' active scenario
A64: → Monthly profit after overhead at that volume (£) | B64: =(B63/'Bin Stickers 100x140 4pk'!B7)*B54-B60 -> -81.037499
A66: If profit per pack before overhead is zero or negative, the break-even figures show N/A. Overhead is shown as a fixed monthly amount rather than per pack, because per-pack overhead depends on volume.

Sheet Bin Stickers 100x140 4pk
A1: Bin Stickers — 100×140mm, 4-Pack (1 A4 sheet) — Cost Breakdown
A2: Blue = editable input. Black = calculated. Green = linked from another sheet. Yellow highlight = key assumption to review. GBP. Layout (v10): 1 Product → 2 Packing → 3 Shipping → Total cost per pack at the bottom.
A4: PRODUCT SPEC
A5: Item | B5: Value | C5: Notes
A6: Sticker size (mm) | B6: 100 x 140 | C6: Reduced from 150mm to fit 4-up on a single A4 sheet with cutting margin (mathematical max for 2x2 grid is 105x148.5mm = A6; trimmed further to leave a clean guillotine-cut margin (cutting method updated July 2026 — see Business Plan Section 10; no longer uses Cricut Print Then Cut for this product)). Matches the reference listing's overall concept, just resized to fit one page. Note (Aug 2026): the landscape 140x100mm line (D01-D03) has identical area to this 100x140mm portrait sheet, so it fits 4-up on one A4 page the same way and this sheet's materials cost figures (rows 12-18) apply unchanged -- no separate cost row added for it. See Bin-Sticker-Shipping-Plan.md for the packaging question, which does differ by shape.
A7: Stickers per pack | B7: 4 | C7: Standard pack size in this category
A8: A4 pages needed per pack | B8: 1 | C8: Updated: at 100x140mm, all 4 stickers fit on a single A4 sheet (2x2 grid, ~8-8.5mm margin around each). No longer needs 2 sheets — this halves the materials cost per pack vs the original 150mm-tall version.
A10: 1. PRODUCT — what it costs to make one pack of 4 stickers
A11: 1a. Sticker sheet materials (per A4 page)
A12: Item | B12: Cost (£) | C12: Notes
A13: Vinyl (printable, per A4 sheet) | B13: 0.35 | C13: Per A4 sheet, from the Cricut 20-ct set (£6.50 vinyl per 20 sheets, ex-shipping) — see 'cost per item' sheet. Stickiply's per-sheet cost is higher at small pack sizes. Value confirmed by user Sep 2026.
A14: Laminate (cold, per A4 sheet) | B14: 0.35 | C14: Per A4 sheet, from the Cricut 20-ct set (£6.50 laminate per 20 sheets, ex-shipping) — see 'cost per item' sheet. Value confirmed by user Sep 2026.
A15: Ink (colour, per A4 page) | B15: 0.1 | C15: £0.10 per page — deliberate conservative placeholder (user, Sep 2026); not yet calibrated. EcoTank's real cost is likely lower (under 1p/page at 5% coverage in ISO tests) — refine once you can measure bottle depletion on real designs.
A16: Subtotal: cost per A4 page (vinyl + laminate + ink) | B16: =SUM(B13:B15) -> 0.8
A17: Pages per pack (from Product Spec above) | B17: =B8 -> 1
A18: → Sticker sheet materials per pack | B18: =B16*B17 -> 0.8
A20: 1b. Cricut cutting — main kiss-cut + back cut (mat and blade costs on the 'Cricut Costs' sheet)
A21: Item | B21: Value | C21: Notes
A22: Main kiss-cut on the Cricut? (Y/N) | B22: N | C22: v9: N per your v8 edit ('no need thanks to back cut – Liron'). Set Y if the front kiss-cut pass comes back.
A23: Sticker sheets cut per pack | B23: =B8 -> 1 | C23: Linked to A4 pages per pack (Product Spec).
A24: Mat used | B24: ='Cricut Costs'!B24 -> StandardGrip 12x12 | C24: From the 'Main kiss-cut' job on the Cricut Costs sheet — change the mat there.
A25: → Mat cost per use (£) | B25: ='Cricut Costs'!E24 -> 0.07037037
A26: Blade used | B26: ='Cricut Costs'!C24 -> Fine-point (Premium)
A27: → Blade cost per cut (£) | B27: ='Cricut Costs'!F24 -> 0.0225
A28: → Cricut cost per sheet cut (£) | B28: ='Cricut Costs'!G24 -> 0.09287037
A29: → Main kiss-cut cost per pack | B29: =IF(B22="Y",B28*B23,0) -> 0 | C29: Driven by the Y/N toggle in B22.
A30: Back cut made on the Cricut? (Y/N) | B30: Y | C30: Y = a second Cricut pass with the sticker sheet face down, cutting a slit through the backing only, 15mm from the top edge of each sticker. Assumed to cost one extra mat use + one blade cut per sticker sheet — confirm once timed and tested.
A31: → Back cut cost per pack (one pass per sticker sheet) | B31: =IF(B30="Y",'Cricut Costs'!G25*B8,0) -> 0.28916667 | C31: 'Back cut' job on the Cricut Costs sheet (12x24 StandardGrip) × sheets per pack. Toggle in B30.
A32: → Cricut cutting cost per pack (main cut + back cut) | B32: =B29+B31 -> 0.28916667
A34: 1c. Peel markers ('PEEL THIS FIRST' pill + arrow, one set per sticker)
A35: Item | B35: Value | C35: Notes
A36: Marker sheet price (£) — same SmithPackaging label sheets as the logo sticker | B36: =B83 -> 0.0899 | C36: Linked to B83 (logo sticker sheet, £8.99 ÷ 100 sheets).
A37: Ink per marker sheet (£) | B37: =B15 -> 0.1 | C37: Linked to the £0.10 per page ink placeholder. Solid magenta pills and arrows cover roughly a fifth of the sheet.
A38: Cricut cost per marker sheet (Print Then Cut: one mat use + one blade cut) | B38: ='Cricut Costs'!G27 -> 0.09287037 | C38: v9: from the 'Peel marker sheet Print Then Cut' job on the Cricut Costs sheet (12x12 StandardGrip).
A39: → Total cost per marker sheet | B39: =B36+B37+B38 -> 0.28277037
A40: Marker sets per A4 sheet (1 pill + 1 arrow per set) | B40: 35 | C40: Entered by user, Oct 2026: 35 sets per sheet, tested.
A41: → Cost per marker set | B41: =B39/B40 -> 0.0080791534
A42: Marker sets per pack (one per sticker) | B42: =B7 -> 4 | C42: Linked to Stickers per pack.
A43: → Marker cost per pack | B43: =B41*B42 -> 0.032316614
A45: SUBTOTAL 1 — PRODUCT COST PER PACK | B45: =B18+B32+B43 -> 1.1214833 | C45: Sticker sheet materials + Cricut cutting + peel markers.
A47: 2. PACKING — envelope, inserts and wrap
A48: 2a. Envelope + seal tape (options from Test 6 — see Bin-Sticker-Material-Test-Plan.md)
A49: Option | B49: Cost/pack (£) | C49: Notes
A50: Kraft envelope + tissue (flat wrap) | B50: 0.08 | C50: Cheapest, lowest transit protection — sheet can flex/crease in a stuffed mailbag. Materials: C6 kraft envelope (~£6-7/50, Amazon UK) + tissue offcut. Packed thickness <1mm — qualifies for Royal Mail Letter rate, not just Large Letter. Matches what most Etsy bin-sticker/decal sellers use as default (see Competitor Research).
A51: Kraft envelope + rigid backing card (no padding) | B51: 0.15 | C51: Same envelope as above, tissue swapped for a rigid cardstock backing card (made in-house from offcuts, near-zero marginal cost per Business Plan Section 7). Resists bending/creasing without adding real thickness (~0.5mm) — the one candidate that might combine Letter-rate postage with better-than-plain-wrap protection. No cushioning against knocks/crushing, unlike a padded mailer or box.
A52: Padded mailer (Mail Lite A/000, 110×160mm) | B52: 0.15 | C52: Cushions knocks in transit, stays flat and cheap to post. ~£11.66/100 (~5g each), confirmed by supplier as Royal Mail Large Letter sized. Packed thickness ~5-10mm — the padding itself rules out the Letter rate; no genuinely thin padded/bubble mailer exists that fits under 5mm.
A53: C6 box (163×112×20mm, rigid) | B53: 0.14 | C53: Best transit protection and strongest 'unboxing' presentation — matches the gift-feel packaging described in Business Plan Section 7. £6.54-6.89/50 (Forms Plus). 20mm depth stays under the 25mm Royal Mail Large Letter thickness limit, but is well over the 5mm Letter limit.
A54: A6/C6 board-backed 'Do Not Bend' envelope (flat) | B54: 0.25 | C54: Confirmed choice (Sep 2026), ~£0.25 per pack (sourced). Not one of the original four Test 6 candidates — Test 6 still needs to validate it in the post. Note the R&D test purchase (Double Dragon 50-pack) works out at £0.147 each: reconcile which supplier you will actually use.
A55: Selected packaging option (confirmed Sep 2026; Test 6 still to validate) | B55: A6/C6 board-backed 'Do Not Bend' envelope (flat) | C55: Oct 2026: switched from 'Kraft envelope + rigid backing card' to the A6/C6 board-backed envelope, the confirmed choice (Merge notes said it was selected, but v4 still pointed at the backing card at £0.15). Still must match one of A50:A54 exactly. Tape and the AKAR multi-pack box are costed on the 'Packing Oct 2026' tab.
A56: → Packaging cost per pack (pulled from selection above) | B56: =INDEX(B50:B54,MATCH(B55,A50:A54,0)) -> 0.25
A57: Seal tape per envelope (£) | B57: ='Packing Oct 2026'!B18 -> 0.0594 | C57: Linked from the Packing Oct 2026 tab (Sellotape Zero Plastic, 30cm per envelope as measured). Box orders use that tab's per-pack box figure instead.
A58: → Envelope + seal tape per pack | B58: =B56+B57 -> 0.3094
A60: 2b. Personal wrap (small 140x100mm only; see sticker_wrap_README.md)
A61: Item | B61: Value | C61: Notes
A62: Paper pack price (£) — plain 120gsm A4 | B62: 8 | C62: Entered by user, Oct 2026: £8 for 250 sheets. White or kraft.
A63: Sheets per pack | B63: 250
A64: → Price per A4 sheet | B64: =B62/B63 -> 0.032
A65: Wraps per A4 sheet | B65: 1 | C65: The wrap net is 180 x 232mm, so one per sheet (sticker_wrap.py).
A66: → Paper cost per wrap | B66: =B64/B65 -> 0.032
A67: Ink per wrap (£) | B67: =B15 -> 0.1 | C67: Linked to the £0.10 per page ink placeholder (B15). Coverage is light (text, half-size design preview, logo), so the real figure is likely lower.
A68: Cut on the Cricut? (Y/N) | B68: Y | C68: Y = Print Then Cut (adds one mat use + one blade cut per wrap). N = scissors by hand (no machine cost). Defaulted to Y as the conservative figure.
A69: → Cricut cost per wrap (mat use + blade cut) | B69: =IF(B68="Y",'Cricut Costs'!G26,0) -> 0.09287037 | C69: v9: from the 'Wrap Print Then Cut' job on the Cricut Costs sheet (12x12 StandardGrip). Add a LightGrip mat there and switch the job's dropdown if you move paper to LightGrip.
A70: → Wrap cost per pack | B70: =B66+B67+B69 -> 0.22487037
A71: Wrap weight (g, 120gsm) | B71: 4.1 | C71: Calculated from the net area (34,463 mm²) at 120gsm; ~3.4g at 100gsm. Add to packed weights in the Shipping Plan.
A73: 2c. Thank-you card (1 per order; see Business Plan Section 7)
A74: Item | B74: Cost (£) | C74: Notes
A75: Cardstock (per card — 1/4 of an A4 250gsm sheet, white or kraft) | B75: 0.06 | C75: A4 250gsm cardstock ~£0.08/sheet ÷ 4 cards (A6 size, exactly 1/4 of A4, cut with the guillotine) = £0.02/card. Kraft cardstock runs higher (~£0.15-0.30/sheet ÷ 4 ≈ £0.04-0.08/card) — this figure uses the white/cream cardstock estimate; edit this cell if you settle on kraft instead.
A76: Ink (light coverage — flower motif + text, much lighter than a full sticker print) | B76: 0.1 | C76: Same £0.10 per page placeholder as the sticker ink above (user, Sep 2026). Light coverage means the true cost is lower.
A77: Subtotal: thank-you card cost per pack | B77: =SUM(B75:B76) -> 0.16
A79: 2d. Logo sticker (edit £/counts below as needed)
A80: Item | B80: Cost (£) | C80: Notes
A81: SmithPackaging A4 self-adhesive label sheets (1 label per sheet, 100) — pack price (£) | B81: 8.99 | C81: Entered by user, Oct 2026: £8.99 for 100 sheets. Regular (non-waterproof) paper labels, used for the 40mm seal sticker, which sits under clear tape on the envelope. Same product as the R&D address-label row on the Tier 1 sheet.
A82: Sheets per pack | B82: 100
A83: → Price per sheet | B83: =B81/B82 -> 0.0899
A84: Ink cost per sheet (£) | B84: 0.1
A85: → Total cost per sheet (material + ink) | B85: =B83+B84 -> 0.1899
A86: Logo stickers per sheet | B86: 24
A87: → Cost per logo sticker (total sheet cost ÷ stickers per sheet) | B87: =B85/B86 -> 0.0079125
A88: Logo stickers included per pack | B88: 1 | C88: Assumption — one logo sticker included per pack; edit if more are included.
A89: Subtotal: Logo sticker cost per pack | B89: =B87*B88 -> 0.0079125
A91: SUBTOTAL 2 — PACKING COST PER PACK | B91: =B58+B70+B77+B89 -> 0.70218287 | C91: Envelope + seal tape + personal wrap + thank-you card + logo sticker. Multi-pack orders in the AKAR box are costed on the 'Packing Oct 2026' tab.
A93: 3. SHIPPING — Royal Mail postage + address label
A94: 3a. Royal Mail postage (Letter/Large Letter checked July 2026; Tracked updated 6 Oct 2026)
A95: Service | B95: Price (£) | C95: Notes
A96: 2nd Class Standard (untracked) — Letter, up to 100g | B96: 0.91 | C96: Royal Mail Letter rate unchanged at £0.91 after the 5 Oct 2026 price change. For eBay orders, confirm eBay's label tool offers Letter at £0.91 at the first order; if it only offers Large Letter, buy that label in Click & Drop instead. Only available if the packed item is under 240x165x5mm and 100g.
A97: 2nd Class Standard (untracked) — Large Letter, up to 100g | B97: 1.55 | C97: Default/standard tier per Business Plan Section 8 — typically absorbed into item price, not charged separately at checkout. The only option available for the padded mailer and box candidates, since their thickness rules out the Letter rate.
A98: 2nd Class (untracked) — Large Letter, up to 250g | B98: 1.9 | C98: Applies if the packed 4-pack + packaging crosses the 100g threshold — confirm on a kitchen scale.
A99: Tracked 48 — Large Letter | B99: 2.9 | C99: Royal Mail online price for Tracked 48 Large Letter from 5 Oct 2026 (was £2.75). Not offered at launch (free 2nd Class only). If added as a buyer-paid upgrade, break-even charge is about £2.37-2.51 after eBay fees on postage; suggested £2.69. The Business Plan's earlier +£1.50-2.00 example would lose money.
A100: Tracked 24 — Large Letter | B100: 3.9 | C100: Royal Mail online price for Tracked 24 Large Letter from 5 Oct 2026 (was £3.65). 'Aims for' next working day, not a guarantee. Not offered at launch. Break-even charge about £3.55-3.77; suggested £3.99. The earlier +£3.00 example would lose money.
A101: Special Delivery Guaranteed by 1pm | B101: 8.75 | C101: For bundled/high-value orders (£20+) only, per Business Plan Section 8. Royal Mail raised Special Delivery by £0.70-3.20 on 5 Oct 2026; £8.75 not re-checked.
A102: Selected shipping tier (for landed cost below) | B102: 2nd Class Standard (untracked) — Letter, up to 100g | C102: Oct 2026: Letter (£0.91) selected for a single pack in the A6/C6 board-backed envelope - packed thickness reported under 4mm, to be confirmed at the Post Office gauge. If it gauges 5mm or more, switch to the Large Letter row. Multi-pack orders in the AKAR box use Large Letter - see 'Packing Oct 2026'. Must exactly match one of A96:A101.
A103: → Shipping cost per pack (pulled from selection above) | B103: =INDEX(B96:B101,MATCH(B102,A96:A101,0)) -> 0.91
A105: 3b. Address label (Click & Drop)
A106: Item | B106: Value | C106: Notes
A107: A4 self-adhesive address label pack — price (£) | B107: 0 | C107: Oct 2026: set to £0 - labels are printed free at the Post Office via Click & Drop (QR code), so no label stock is consumed. Previous value £32.21 (SmithPackaging 100-sheet pack; note the Shipping Plan quotes £9). Restore if printing at home. Flows through to the 202x140 and 280x200 sheets.
A108: Sheets per pack | B108: 25
A109: → Price per A4 sheet | B109: =B107/B108 -> 0
A110: Labels printed per sheet (batch assumption) | B110: 3 | C110: This product is one full-A4 label per sheet (199.6 x 289.1mm), so 1 label per sheet is assumed (conservative). If you print 3 shipping labels on one sheet and cut them apart, set this to 3 (cost falls to £0.03). Plain paper + tape (~1-2p) is also officially supported by Royal Mail.
A111: → Cost per address label (sheet price ÷ labels used) | B111: =B109/B110 -> 0
A113: SUBTOTAL 3 — SHIPPING COST PER PACK | B113: =B103+B111 -> 0.91 | C113: Postage + address label.
...

Sheet Packing Oct 2026
A1: Packing update - AKAR multi-pack box and clear tape (Oct 2026, GBP)
A2: Blue = editable input. Yellow = still needed from you (left blank, so costs show £0 until filled). Black = calculated.
A4: AKAR WHITE A6/C6 LARGE LETTER BOX
A5: Box pack price (£) | C5: NEEDED: price you paid for the AKAR box pack.
A6: Boxes in pack | C6: NEEDED: boxes per pack.
A7: → Cost per box (£) | B7: =IF(OR(B5="",B6=""),0,B5/B6) -> 0
A8: Packs per box (cap) | B8: 4 | C8: Tested Oct 2026: 4 packs = 82g (about 84g taped), box 23mm. 5 would be ~97g, too close to 100g.
A9: Weight - box + 4 packs + tape (g) | B9: 84 | C9: 82g measured without tape + ~2g tape (measured on the 2-pack box).
A10: → Box cost per pack, excl. tape (£) | B10: =IF(B8=0,0,B7/B8) -> 0
A12: CLEAR PLANT-BASED TAPE — Sellotape Zero Plastic, 24mm x 30m (selected Oct 2026)
A13: Roll price (£) | B13: 5.94 | C13: GreenStat UK listing, £5.94 inc VAT, checked Oct 2026. Cellulose film, plastic-free; the tape itself is compostable, not recyclable.
A14: Roll length (m) | B14: 30 | C14: 30m per roll (same listing).
A15: Tape used per envelope (cm) | B15: 30 | C15: Measured by you with regular tape, Oct 2026. If you only tape over the 40mm seal sticker (~7cm strip), set this to 7.
A16: Tape used per box (cm) | B16: 45 | C16: Measured by you, Oct 2026.
A17: → Cost per cm (£) | B17: =IF(OR(B13="",B14="",B14=0),0,B13/(B14*100)) -> 0.00198
A18: → Tape cost per envelope parcel (£) | B18: =B17*B15 -> 0.0594
A19: → Tape cost per box parcel (£) | B19: =B17*B16 -> 0.0891
A20: → Tape cost per pack when shipped in the box (£) | B20: =IF(B8=0,0,B19/B8) -> 0.022275
A22: PER-PACK PACKAGING + POSTAGE COMPARISON
B23: 1 pack (envelope, Letter) | C23: 4 packs (AKAR box, Large Letter)
A24: Packaging per pack (£) | B24: ='Bin Stickers 100x140 4pk'!B56 -> 0.25 | C24: =B10 -> 0
A25: Tape per pack (£) | B25: =B18 -> 0.0594 | C25: =B20 -> 0.022275
A26: Postage per parcel (£) | B26: ='Bin Stickers 100x140 4pk'!B96 -> 0.91 | C26: ='Bin Stickers 100x140 4pk'!B97 -> 1.55
A27: Postage per pack (£) | B27: =B26 -> 0.91 | C27: =IF(B8=0,0,C26/B8) -> 0.3875
A28: Packaging + tape + postage per pack (£) | B28: =B24+B25+B27 -> 1.2194 | C28: =C24+C25+C27 -> 0.409775
A29: Saving per pack in the box vs envelope (£) | C29: =B28-C28 -> 0.809625
A31: Notes: Letter £0.91 and Large Letter £1.55 are the cost-sheet figures - confirm in Click & Drop. Box postage assumes ≤100g (84g with 4 packs). The 4-pack box is for orders of multiple packs; a single pack should still ship in the envelope. Tape and the AKAR box are NOT yet added into the totals on the 100x140 sheet - decide once prices are in.

Sheet Bin Stickers 202x140 2pk
A1: Bin Stickers — 202×140mm, 2-Pack (1 A4 sheet) — Cost Breakdown
A2: Blue = editable input. Black = calculated. Green = linked from another sheet (mostly the 100x140 baseline). Yellow highlight = key assumption to review. GBP. Layout (v11): 1 Product → 2 Packing → 3 Shipping → Total cost per pack at the bottom.
A4: PRODUCT SPEC
A5: Item | B5: Value | C5: Notes
A6: Sticker size (mm) | B6: 202 x 140 | C6: New MEDIUM tier: 202×140mm, two stacked per A4 sheet. Trimmed from 210mm (Sep 2026) so it prints in NORMAL (bordered) mode — the Epson EcoTank ET-3950's normal printable width is 204mm, leaving about 1mm spare each side — which avoids the borderless dead zone (~2-4mm, asymmetric) measured in the earlier print test. Two 140mm cards stack to 280mm, which is the maximum height inside the measured 8.5mm top/bottom margins. Close to the 21×14cm size sold by a real competitor (House Number & Address Decals shop, 4.7★/3.1k reviews — see Competitor Research). Print margins should be confirmed with a print test at this exact size.
A7: Stickers per pack | B7: 2 | C7: Two 202×140mm cards stack to 280mm, the maximum height inside the measured 8.5mm top/bottom margins. Sold as a pair, matching the competitor benchmark this size is based on.
A8: A4 pages needed per pack | B8: 1 | C8: Still 1 A4 page per pack, same as baseline — the sheet math changes (2 stickers instead of 4), not the page count.
A10: 1. PRODUCT — what it costs to make one pack (2 stickers)
A11: 1a. Sticker sheet materials (per A4 page)
A12: Item | B12: Cost (£) | C12: Notes
A13: Vinyl (printable, per A4 sheet) | B13: ='Bin Stickers 100x140 4pk'!B13 -> 0.35 | C13: Linked to the baseline sheet (same material for all size tiers).
A14: Laminate (cold, per A4 sheet) | B14: ='Bin Stickers 100x140 4pk'!B14 -> 0.35 | C14: Linked to the baseline sheet (same material for all size tiers).
A15: Ink (colour, per A4 page) | B15: ='Bin Stickers 100x140 4pk'!B15 -> 0.1 | C15: Linked to the baseline sheet (same £0.10 placeholder) — NOT yet re-tested for this size.
A16: Subtotal: cost per A4 page (vinyl + laminate + ink) | B16: =SUM(B13:B15) -> 0.8
A17: Pages per pack (from Product Spec above) | B17: =B8 -> 1
A18: → Sticker sheet materials per pack | B18: =B16*B17 -> 0.8
A20: 1b. Cricut cutting — main kiss-cut + back cut (mat and blade costs on the 'Cricut Costs' sheet)
A21: Item | B21: Value | C21: Notes
A22: Main kiss-cut on the Cricut? (Y/N) | B22: Y | C22: v9: Y = unchanged from v8 (this tab still costed the main cut). Set N if the back cut replaces the front pass for this size too, as on the 100x140 tab.
A23: Sticker sheets cut per pack | B23: =B8 -> 1 | C23: Linked to A4 pages per pack (Product Spec).
A24: Mat used | B24: ='Cricut Costs'!B24 -> StandardGrip 12x12 | C24: From the 'Main kiss-cut' job on the Cricut Costs sheet — change the mat there.
A25: → Mat cost per use (£) | B25: ='Cricut Costs'!E24 -> 0.07037037
A26: Blade used | B26: ='Cricut Costs'!C24 -> Fine-point (Premium)
A27: → Blade cost per cut (£) | B27: ='Cricut Costs'!F24 -> 0.0225
A28: → Cricut cost per sheet cut (£) | B28: ='Cricut Costs'!G24 -> 0.09287037
A29: → Main kiss-cut cost per pack | B29: =IF(B22="Y",B28*B23,0) -> 0.09287037 | C29: Driven by the Y/N toggle in B22.
A30: Back cut made on the Cricut? (Y/N) | B30: ='Bin Stickers 100x140 4pk'!B30 -> Y | C30: Linked from the baseline 100x140 sheet.
A31: → Back cut cost per pack (one pass per sticker sheet) | B31: =IF(B30="Y",'Cricut Costs'!G25*B8,0) -> 0.28916667 | C31: 'Back cut' job on the Cricut Costs sheet (12x24 mat) × sheets per pack. Toggle in B30 is linked from the baseline 100x140 tab.
A32: → Cricut cutting cost per pack (main cut + back cut) | B32: =B29+B31 -> 0.38203704
A34: 1c. Peel markers ('PEEL THIS FIRST' pill + arrow, one set per sticker)
A35: Item | B35: Value | C35: Notes
A36: Cost per marker set | B36: ='Bin Stickers 100x140 4pk'!B41 -> 0.0080791534 | C36: Linked from the baseline 100x140 sheet.
A37: Marker sets per pack (one per sticker) | B37: =B7 -> 2 | C37: Linked to Stickers per pack.
A38: → Marker cost per pack | B38: =B36*B37 -> 0.016158307
A40: SUBTOTAL 1 — PRODUCT COST PER PACK | B40: =B18+B32+B38 -> 1.1981953 | C40: Sticker sheet materials + Cricut cutting + peel markers.
A42: 2. PACKING — envelope and inserts
A43: 2a. Envelope (re-sized for 202x140mm — the baseline's envelopes are too small; options pending Test 6)
A44: Option | B44: Cost/pack (£) | C44: Notes
A45: C4 kraft envelope + tissue (flat wrap) | B45: 0.22 | C45: C4 (229x324mm) is used as a placeholder. At 202×140mm the card also fits a C5 (229×162mm), the smaller standard size, which would likely be cheaper — swap in a sourced C5 price. Plain white C4 self-seal runs ~£0.25-0.30/envelope in small packs (25s) on Amazon UK, cheaper in bulk — £0.22 used as a bulk-pack estimate; confirm at your actual order size. + tissue offcut, near-zero marginal cost.
A46: C4 kraft envelope + rigid backing card (no padding) | B46: 0.24 | C46: Same C4 envelope as above, tissue swapped for an in-house-cut rigid cardstock backing sized to the card -- resists bending in transit for a ~£0.02 premium, same logic as the baseline's backing-card option.
A47: C4 padded mailer | B47: 0.35 | C47: UK C4-size padded mailers run roughly £0.30-0.40 each in bulk packs -- placeholder, confirm against a specific UK listing before committing (not yet checked as precisely as the C4 plain envelope above).
A48: A4/C4 box (rigid, for premium presentation) | B48: 0.45 | C48: Placeholder only -- rigid boxes sized for a 202x140mm card weren't priced in this pass. Treat as a rough order-of-magnitude figure (baseline's C6 box was £0.14 at a much smaller size) until a real UK listing is checked.
A49: Selected packaging option (pending Test 6 results) | B49: C4 kraft envelope + tissue (flat wrap) | C49: Placeholder default = cheapest option, matching baseline's convention. Update once you test real packaging for this size.
A50: → Packaging cost per pack (pulled from selection above) | B50: =INDEX(B45:B48,MATCH(B49,A45:A48,0)) -> 0.22
A52: 2b. Thank-you card (1 per order; see Business Plan Section 7)
A53: Item | B53: Cost (£) | C53: Notes
A54: Cardstock (per card — 1/4 of an A4 250gsm sheet, white or kraft) | B54: ='Bin Stickers 100x140 4pk'!B75 -> 0.06 | C54: A4 250gsm cardstock ~£0.08/sheet ÷ 4 cards (A6 size, exactly 1/4 of A4, cut with the guillotine) = £0.02/card. Kraft cardstock runs higher (~£0.15-0.30/sheet ÷ 4 ≈ £0.04-0.08/card) — this figure uses the white/cream cardstock estimate; edit this cell if you settle on kraft instead.
A55: Ink (light coverage — flower motif + text, much lighter than a full sticker print) | B55: ='Bin Stickers 100x140 4pk'!B76 -> 0.1 | C55: Printed via the same Epson EcoTank printer/ink used for stickers — light line-art + text coverage, well under the ~£0.05/page ink assumption used for the dense sticker designs above (row 14).
A56: Subtotal: thank-you card cost per pack | B56: =SUM(B54:B55) -> 0.16
A58: 2c. Logo sticker (linked from the baseline 100x140 sheet)
A59: Item | B59: Cost (£) | C59: Notes
A60: Waterproof sticker sheet — pack price (£) | B60: ='Bin Stickers 100x140 4pk'!B81 -> 8.99 | C60: Linked to the baseline sheet (same material for all size tiers).
A61: Sheets per pack | B61: ='Bin Stickers 100x140 4pk'!B82 -> 100
A62: → Price per sheet | B62: =B60/B61 -> 0.0899
A63: Ink cost per sheet (£) | B63: ='Bin Stickers 100x140 4pk'!B84 -> 0.1 | C63: Linked to the baseline sheet (same £0.10 placeholder).
A64: → Total cost per sheet (material + ink) | B64: =B62+B63 -> 0.1899
A65: Logo stickers per sheet | B65: ='Bin Stickers 100x140 4pk'!B86 -> 24
A66: → Cost per logo sticker (total sheet cost ÷ stickers per sheet) | B66: =B64/B65 -> 0.0079125
A67: Logo stickers included per pack | B67: ='Bin Stickers 100x140 4pk'!B88 -> 1 | C67: Linked to the baseline sheet — one logo sticker included per pack, regardless of size tier.
A68: Subtotal: Logo sticker cost per pack | B68: =B66*B67 -> 0.0079125
A70: SUBTOTAL 2 — PACKING COST PER PACK | B70: =B50+B56+B68 -> 0.3879125 | C70: Envelope + thank-you card + logo sticker. No personal wrap or seal tape on this size (those are costed on the 100x140 tab only).
A72: 3. SHIPPING — Royal Mail postage + address label
A73: 3a. Royal Mail postage (estimated prices, checked July 2026 — linked from the baseline)
A74: Service | B74: Price (£) | C74: Notes
A75: 2nd Class Standard (untracked) — Letter, up to 100g | B75: ='Bin Stickers 100x140 4pk'!B96 -> 0.91 | C75: Sources show ~85-91p for the current rate — confirm the exact figure in Click & Drop at checkout; £0.88 used here as a midpoint placeholder. Only available if the packed item is under 240x165x5mm and 100g — realistically only the flat-wrap and backing-card packaging options qualify (see Packaging Options above).
A76: 2nd Class Standard (untracked) — Large Letter, up to 100g | B76: ='Bin Stickers 100x140 4pk'!B97 -> 1.55 | C76: Default/standard tier per Business Plan Section 8 — typically absorbed into item price, not charged separately at checkout. The only option available for the padded mailer and box candidates, since their thickness rules out the Letter rate.
A77: 2nd Class (untracked) — Large Letter, up to 250g | B77: ='Bin Stickers 100x140 4pk'!B98 -> 1.9 | C77: Applies if the packed 4-pack + packaging crosses the 100g threshold — confirm on a kitchen scale.
A78: Tracked 48 — Large Letter | B78: ='Bin Stickers 100x140 4pk'!B99 -> 2.9 | C78: Optional paid upgrade (+£1.50-2.00 over standard per Business Plan Section 8).
A79: Tracked 24 — Large Letter | B79: ='Bin Stickers 100x140 4pk'!B100 -> 3.9 | C79: Optional paid upgrade (+£3.00). 'Aims for' next working day — not a guarantee.
A80: Special Delivery Guaranteed by 1pm | B80: ='Bin Stickers 100x140 4pk'!B101 -> 8.75 | C80: For bundled/high-value orders (£20+) only, per Business Plan Section 8 — not the standard single-pack tier.
A81: Selected shipping tier (for landed cost below) | B81: 2nd Class (untracked) — Large Letter, up to 250g | C81: Unlike the baseline 140x100mm product, this size can NEVER use the cheaper Letter-rate tier -- Royal Mail's Letter format caps out at 165mm width, and this card is 202mm wide on its own before any envelope. Large Letter is the floor for this size, regardless of packaging choice. Defaulted to the 250g band rather than 100g since an envelope + vinyl + laminate + backing card is more likely to cross 100g than the baseline's smaller envelope -- confirm on a kitchen scale once packaged.
A82: → Shipping cost per pack (pulled from selection above) | B82: =INDEX(B75:B80,MATCH(B81,A75:A80,0)) -> 1.9
A84: 3b. Address label (Click & Drop)
A85: Item | B85: Value | C85: Notes
A86: A4 sticker label sheet pack — price (£) | B86: ='Bin Stickers 100x140 4pk'!B107 -> 0 | C86: Linked to the baseline sheet (SmithPackaging label pack).
A87: Sheets per pack | B87: ='Bin Stickers 100x140 4pk'!B108 -> 25
A88: → Price per A4 sheet | B88: =B86/B87 -> 0
A89: Labels printed per sheet (batch assumption) | B89: ='Bin Stickers 100x140 4pk'!B110 -> 3 | C89: Assumes you batch 3 shipments' worth of labels onto one sheet before cutting (Click & Drop '3+ per A4' style batching), rather than 1 label per sheet. Sheet has 21 slots total - this treats the other 18 as unused/wasted per batch, which is the conservative per-shipment cost. Increase this number if you routinely batch more orders together. Cheaper default at low volume: plain A4 paper + tape/glue stick (~1-2p/shipment), officially supported by Royal Mail.
A90: → Cost per address label (sheet price ÷ labels used) | B90: =B88/B89 -> 0
A92: SUBTOTAL 3 — SHIPPING COST PER PACK | B92: =B82+B90 -> 1.9 | C92: Postage + address label.
A94: TOTAL COST PER PACK
A95: Item | B95: Cost per pack (£) | C95: Notes
A96: 1. Product | B96: =B40 -> 1.1981953
A97: 2. Packing | B97: =B70 -> 0.3879125
A98: 3. Shipping | B98: =B92 -> 1.9
A99: TOTAL LANDED COST PER PACK (product + packing + shipping) | B99: =B96+B97+B98 -> 3.4861078 | C99: Direct cost per pack, excl. recurring overhead.
A100: Cost per individual sticker (all-in incl. packing + shipping) | B100: =B99/B7 -> 1.7430539
A102: Overhead cost per sticker (£) | B102: ='Recurring Overhead'!B34 -> 8.3223333 | C102: Live link to the Recurring Overhead sheet's ACTIVE SCENARIO figure (subscriptions ÷ chosen scenario's monthly volume). Defaults to the Conservative scenario — change the dropdown on that sheet to switch which scenario feeds this and the Break-Even Calculator.
A103: Overhead cost per pack (2 stickers) (£) | B103: =B102*B7 -> 16.644667
A104: TOTAL LANDED COST PER PACK, INCL. OVERHEAD (£) | B104: =B99+B103 -> 20.130775
A105: Cost per individual sticker, incl. overhead (£) | B105: =B104/B7 -> 10.065387
A107: Shipping (postage) is typically absorbed into the item's list price rather than charged separately at checkout (standard/free shipping is the competitor norm — see Business Plan Section 8), so the TOTAL LANDED COST row is your true all-in cost basis for pricing. To re-model, change 'Selected packaging option' (B49) or 'Selected shipping tier' (B81).
A108: Direct cost per pack is B99 (excludes recurring overhead). B104 is the all-in floor price if the active overhead scenario were spread across every sticker.

Sheet Bin Stickers 280x200 1pk
A1: Bin Stickers — 280×200mm, Single (1 A4 sheet) — Cost Breakdown
A2: Blue = editable input. Black = calculated. Green = linked from another sheet (mostly the 100x140 baseline). Yellow highlight = key assumption to review. GBP. Layout (v11): 1 Product → 2 Packing → 3 Shipping → Total cost per pack at the bottom.
A4: PRODUCT SPEC
A5: Item | B5: Value | C5: Notes
A6: Sticker size (mm) | B6: 280 x 200 | C6: New LARGE tier: 280×200mm, i.e. 200mm wide × 280mm tall on the portrait A4 sheet (resized Sep 2026 from 280×200mm). 280mm is the maximum height inside the measured 8.5mm top/bottom margins (297 − 17), and 200mm sits inside the 204mm printable width, so it prints in NORMAL (bordered) mode with no borderless printing. NOT the market's established 30x20cm 'Large' benchmark used by multiple competitors — that size is 3mm longer than A4's own 297mm page length and is physically impossible on A4 regardless of print mode. A true 30x20cm size would need an A3-capable printer later (see Equipment Guide Tier 2/3), not forced onto this A4 workflow. Print margins should be confirmed with a print test at this exact size.
A7: Stickers per pack | B7: 1 | C7: Sold as a single sticker, not a pack — this size doesn't fit 2-up on any orientation of A4, so there's no natural pack size the way the baseline's 4-pack or Medium's 2-pack have.
A8: A4 pages needed per pack | B8: 1 | C8: 1 A4 page per unit — same page count as the other two tiers, just 1 sticker on it instead of 2 or 4.
A10: 1. PRODUCT — what it costs to make one pack (1 sticker)
A11: 1a. Sticker sheet materials (per A4 page)
A12: Item | B12: Cost (£) | C12: Notes
A13: Vinyl (printable, per A4 sheet) | B13: ='Bin Stickers 100x140 4pk'!B13 -> 0.35 | C13: Linked to the baseline sheet (same material for all size tiers).
A14: Laminate (cold, per A4 sheet) | B14: ='Bin Stickers 100x140 4pk'!B14 -> 0.35 | C14: Linked to the baseline sheet (same material for all size tiers).
A15: Ink (colour, per A4 page) | B15: ='Bin Stickers 100x140 4pk'!B15 -> 0.1 | C15: Linked to the baseline sheet (same £0.10 placeholder) — NOT yet re-tested for this size.
A16: Subtotal: cost per A4 page (vinyl + laminate + ink) | B16: =SUM(B13:B15) -> 0.8
A17: Pages per pack (from Product Spec above) | B17: =B8 -> 1
A18: → Sticker sheet materials per pack | B18: =B16*B17 -> 0.8
A20: 1b. Cricut cutting — main kiss-cut + back cut (mat and blade costs on the 'Cricut Costs' sheet)
A21: Item | B21: Value | C21: Notes
A22: Main kiss-cut on the Cricut? (Y/N) | B22: Y | C22: v9: Y = unchanged from v8 (this tab still costed the main cut). Set N if the back cut replaces the front pass for this size too, as on the 100x140 tab.
A23: Sticker sheets cut per pack | B23: =B8 -> 1 | C23: Linked to A4 pages per pack (Product Spec).
A24: Mat used | B24: ='Cricut Costs'!B24 -> StandardGrip 12x12 | C24: From the 'Main kiss-cut' job on the Cricut Costs sheet — change the mat there.
A25: → Mat cost per use (£) | B25: ='Cricut Costs'!E24 -> 0.07037037
A26: Blade used | B26: ='Cricut Costs'!C24 -> Fine-point (Premium)
A27: → Blade cost per cut (£) | B27: ='Cricut Costs'!F24 -> 0.0225
A28: → Cricut cost per sheet cut (£) | B28: ='Cricut Costs'!G24 -> 0.09287037
A29: → Main kiss-cut cost per pack | B29: =IF(B22="Y",B28*B23,0) -> 0.09287037 | C29: Driven by the Y/N toggle in B22.
A30: Back cut made on the Cricut? (Y/N) | B30: ='Bin Stickers 100x140 4pk'!B30 -> Y | C30: Linked from the baseline 100x140 sheet.
A31: → Back cut cost per pack (one pass per sticker sheet) | B31: =IF(B30="Y",'Cricut Costs'!G25*B8,0) -> 0.28916667 | C31: 'Back cut' job on the Cricut Costs sheet (12x24 mat) × sheets per pack. Toggle in B30 is linked from the baseline 100x140 tab.
A32: → Cricut cutting cost per pack (main cut + back cut) | B32: =B29+B31 -> 0.38203704
A34: 1c. Peel markers ('PEEL THIS FIRST' pill + arrow, one set per sticker)
A35: Item | B35: Value | C35: Notes
A36: Cost per marker set | B36: ='Bin Stickers 100x140 4pk'!B41 -> 0.0080791534 | C36: Linked from the baseline 100x140 sheet.
A37: Marker sets per pack (one per sticker) | B37: =B7 -> 1 | C37: Linked to Stickers per pack.
A38: → Marker cost per pack | B38: =B36*B37 -> 0.0080791534
A40: SUBTOTAL 1 — PRODUCT COST PER PACK | B40: =B18+B32+B38 -> 1.1901162 | C40: Sticker sheet materials + Cricut cutting + peel markers.
A42: 2. PACKING — envelope and inserts
A43: 2a. Envelope (re-sized for 280x200mm — the baseline's envelopes are too small; options pending Test 6)
A44: Option | B44: Cost/pack (£) | C44: Notes
A45: C4 kraft envelope + tissue (flat wrap) | B45: 0.22 | C45: C4 (229x324mm) comfortably fits this card (280×200mm) without folding -- same envelope as the Medium placeholder, same ~£0.22/envelope bulk-pack estimate (Amazon UK, checked Sep 2026). + tissue offcut, near-zero marginal cost.
A46: C4 kraft envelope + rigid backing card (no padding) | B46: 0.24 | C46: Same C4 envelope, tissue swapped for a rigid backing card cut to size -- most worth considering for this tier specifically, since a 280mm-long sheet has the most room to flex/crease in transit of all three sizes.
A47: C4 padded mailer | B47: 0.35 | C47: UK C4-size padded mailers run roughly £0.30-0.40 each in bulk packs -- placeholder, confirm against a specific UK listing before committing.
A48: A4/C4 box (rigid, for premium presentation) | B48: 0.45 | C48: Placeholder only -- rigid boxes sized for a near-full-A4 card weren't priced in this pass. Given this is your largest/most premium tier, a rigid box may be worth pricing properly before launch rather than relying on this placeholder.
A49: Selected packaging option (pending Test 6 results) | B49: C4 kraft envelope + rigid backing card (no padding) | C49: Defaulted to the backing-card option rather than plain tissue (unlike the other two tiers) — this is the longest sheet of the three (280mm), giving it the most room to flex/crease in a mailbag, so the extra ~£0.02 for rigidity seems worth it by default. Change if Test 6-equivalent results for this size say otherwise.
A50: → Packaging cost per pack (pulled from selection above) | B50: =INDEX(B45:B48,MATCH(B49,A45:A48,0)) -> 0.24
A52: 2b. Thank-you card (1 per order; see Business Plan Section 7)
A53: Item | B53: Cost (£) | C53: Notes
A54: Cardstock (per card — 1/4 of an A4 250gsm sheet, white or kraft) | B54: ='Bin Stickers 100x140 4pk'!B75 -> 0.06 | C54: A4 250gsm cardstock ~£0.08/sheet ÷ 4 cards (A6 size, exactly 1/4 of A4, cut with the guillotine) = £0.02/card. Kraft cardstock runs higher (~£0.15-0.30/sheet ÷ 4 ≈ £0.04-0.08/card) — this figure uses the white/cream cardstock estimate; edit this cell if you settle on kraft instead.
A55: Ink (light coverage — flower motif + text, much lighter than a full sticker print) | B55: ='Bin Stickers 100x140 4pk'!B76 -> 0.1 | C55: Printed via the same Epson EcoTank printer/ink used for stickers — light line-art + text coverage, well under the ~£0.05/page ink assumption used for the dense sticker designs above (row 14).
A56: Subtotal: thank-you card cost per pack | B56: =SUM(B54:B55) -> 0.16
A58: 2c. Logo sticker (linked from the baseline 100x140 sheet)
A59: Item | B59: Cost (£) | C59: Notes
A60: Waterproof sticker sheet — pack price (£) | B60: ='Bin Stickers 100x140 4pk'!B81 -> 8.99 | C60: Linked to the baseline sheet (same material for all size tiers).
A61: Sheets per pack | B61: ='Bin Stickers 100x140 4pk'!B82 -> 100
A62: → Price per sheet | B62: =B60/B61 -> 0.0899
A63: Ink cost per sheet (£) | B63: ='Bin Stickers 100x140 4pk'!B84 -> 0.1 | C63: Linked to the baseline sheet (same £0.10 placeholder).
A64: → Total cost per sheet (material + ink) | B64: =B62+B63 -> 0.1899
A65: Logo stickers per sheet | B65: ='Bin Stickers 100x140 4pk'!B86 -> 24
A66: → Cost per logo sticker (total sheet cost ÷ stickers per sheet) | B66: =B64/B65 -> 0.0079125
A67: Logo stickers included per pack | B67: ='Bin Stickers 100x140 4pk'!B88 -> 1 | C67: Linked to the baseline sheet — one logo sticker included per pack, regardless of size tier.
A68: Subtotal: Logo sticker cost per pack | B68: =B66*B67 -> 0.0079125
A70: SUBTOTAL 2 — PACKING COST PER PACK | B70: =B50+B56+B68 -> 0.4079125 | C70: Envelope + thank-you card + logo sticker. No personal wrap or seal tape on this size (those are costed on the 100x140 tab only).
A72: 3. SHIPPING — Royal Mail postage + address label
A73: 3a. Royal Mail postage (estimated prices, checked July 2026 — linked from the baseline)
A74: Service | B74: Price (£) | C74: Notes
A75: 2nd Class Standard (untracked) — Letter, up to 100g | B75: ='Bin Stickers 100x140 4pk'!B96 -> 0.91 | C75: Sources show ~85-91p for the current rate — confirm the exact figure in Click & Drop at checkout; £0.88 used here as a midpoint placeholder. Only available if the packed item is under 240x165x5mm and 100g — realistically only the flat-wrap and backing-card packaging options qualify (see Packaging Options above).
A76: 2nd Class Standard (untracked) — Large Letter, up to 100g | B76: ='Bin Stickers 100x140 4pk'!B97 -> 1.55 | C76: Default/standard tier per Business Plan Section 8 — typically absorbed into item price, not charged separately at checkout. The only option available for the padded mailer and box candidates, since their thickness rules out the Letter rate.
A77: 2nd Class (untracked) — Large Letter, up to 250g | B77: ='Bin Stickers 100x140 4pk'!B98 -> 1.9 | C77: Applies if the packed 4-pack + packaging crosses the 100g threshold — confirm on a kitchen scale.
A78: Tracked 48 — Large Letter | B78: ='Bin Stickers 100x140 4pk'!B99 -> 2.9 | C78: Optional paid upgrade (+£1.50-2.00 over standard per Business Plan Section 8).
A79: Tracked 24 — Large Letter | B79: ='Bin Stickers 100x140 4pk'!B100 -> 3.9 | C79: Optional paid upgrade (+£3.00). 'Aims for' next working day — not a guarantee.
A80: Special Delivery Guaranteed by 1pm | B80: ='Bin Stickers 100x140 4pk'!B101 -> 8.75 | C80: For bundled/high-value orders (£20+) only, per Business Plan Section 8 — not the standard single-pack tier.
A81: Selected shipping tier (for landed cost below) | B81: 2nd Class (untracked) — Large Letter, up to 250g | C81: Like the Medium tier, this size can NEVER use the cheaper Letter-rate tier -- both its dimensions (280x200mm) exceed the Letter format's 240x165mm limit. Large Letter is the floor for this size regardless of packaging. Defaulted to the 250g band since a C4 envelope + vinyl + laminate + backing card is more likely to cross 100g than the baseline's smaller envelope -- confirm on a kitchen scale once packaged.
A82: → Shipping cost per pack (pulled from selection above) | B82: =INDEX(B75:B80,MATCH(B81,A75:A80,0)) -> 1.9
A84: 3b. Address label (Click & Drop)
A85: Item | B85: Value | C85: Notes
A86: A4 sticker label sheet pack — price (£) | B86: ='Bin Stickers 100x140 4pk'!B107 -> 0 | C86: Linked to the baseline sheet (SmithPackaging label pack).
A87: Sheets per pack | B87: ='Bin Stickers 100x140 4pk'!B108 -> 25
A88: → Price per A4 sheet | B88: =B86/B87 -> 0
A89: Labels printed per sheet (batch assumption) | B89: ='Bin Stickers 100x140 4pk'!B110 -> 3 | C89: Assumes you batch 3 shipments' worth of labels onto one sheet before cutting (Click & Drop '3+ per A4' style batching), rather than 1 label per sheet. Sheet has 21 slots total - this treats the other 18 as unused/wasted per batch, which is the conservative per-shipment cost. Increase this number if you routinely batch more orders together. Cheaper default at low volume: plain A4 paper + tape/glue stick (~1-2p/shipment), officially supported by Royal Mail.
A90: → Cost per address label (sheet price ÷ labels used) | B90: =B88/B89 -> 0
A92: SUBTOTAL 3 — SHIPPING COST PER PACK | B92: =B82+B90 -> 1.9 | C92: Postage + address label.
A94: TOTAL COST PER PACK
A95: Item | B95: Cost per pack (£) | C95: Notes
A96: 1. Product | B96: =B40 -> 1.1901162
A97: 2. Packing | B97: =B70 -> 0.4079125
A98: 3. Shipping | B98: =B92 -> 1.9
A99: TOTAL LANDED COST PER PACK (product + packing + shipping) | B99: =B96+B97+B98 -> 3.4980287 | C99: Direct cost per pack, excl. recurring overhead.
A100: Cost per individual sticker (all-in incl. packing + shipping) | B100: =B99/B7 -> 3.4980287
A102: Overhead cost per sticker (£) | B102: ='Recurring Overhead'!B34 -> 8.3223333 | C102: Live link to the Recurring Overhead sheet's ACTIVE SCENARIO figure (subscriptions ÷ chosen scenario's monthly volume). Defaults to the Conservative scenario — change the dropdown on that sheet to switch which scenario feeds this and the Break-Even Calculator.
A103: Overhead cost per pack (1 sticker) (£) | B103: =B102*B7 -> 8.3223333
A104: TOTAL LANDED COST PER PACK, INCL. OVERHEAD (£) | B104: =B99+B103 -> 11.820362
A105: Cost per individual sticker, incl. overhead (£) | B105: =B104/B7 -> 11.820362
A107: Shipping (postage) is typically absorbed into the item's list price rather than charged separately at checkout (standard/free shipping is the competitor norm — see Business Plan Section 8), so the TOTAL LANDED COST row is your true all-in cost basis for pricing. To re-model, change 'Selected packaging option' (B49) or 'Selected shipping tier' (B81).
A108: Direct cost per pack is B99 (excludes recurring overhead). B104 is the all-in floor price if the active overhead scenario were spread across every sticker.

Sheet Cricut Costs
A1: Cricut Costs — mats, blades and cutting jobs (added v9, Oct 2026, GBP)
A2: Blue = editable input (yellow = key assumption). Black = calculated. One place for every mat and blade price. Each Cricut job picks its mat and blade from a dropdown, and the bin sticker tabs pull the job cost per sheet from the JOBS table. To add a new mat type (e.g. LightGrip, StrongGrip, another size), fill in a spare row in the MATS table, then pick it in the job's dropdown.
A4: MATS
A5: Mat (name used in the dropdowns) | B5: Size | C5: Grip | D5: Pack price (£) | E5: Mats per pack | F5: → Price per mat (£) | G5: Uses per mat (est.) | H5: → Cost per use (£) | I5: Notes / source
A6: StandardGrip 12x12 | B6: 12 x 12 in (30.5 x 30.5 cm) | C6: StandardGrip (green) | D6: 19 | E6: 6 | F6: =IF(OR(D6="",E6=""),"",D6/E6) -> 3.1666667 | G6: 45 | H6: =IF(OR(F6="",G6=""),"",F6/G6) -> 0.07037037 | I6: User, Oct 2026: £19 for a 6-pack = £3.17 per mat. Uses per mat: third-party consensus ~40–50, no official Cricut figure.
A7: StandardGrip 12x24 | B7: 12 x 24 in (30.5 x 61 cm) | C7: StandardGrip (green) | D7: 24 | E7: 2 | F7: =IF(OR(D7="",E7=""),"",D7/E7) -> 12 | G7: 45 | H7: =IF(OR(F7="",G7=""),"",F7/G7) -> 0.26666667 | I7: User, Oct 2026: £24 for a 2-pack = £12.00 per mat (Cricut UK lists a 4-pack at £32.99 = £8.25 per mat, checked 5 Oct 2026). Used for the back cut. Uses per mat copied from the 12x12 placeholder — revisit with real usage.
F8: =IF(OR(D8="",E8=""),"",D8/E8) | H8: =IF(OR(F8="",G8=""),"",F8/G8) | I8: Spare row — add a future mat type here.
F9: =IF(OR(D9="",E9=""),"",D9/E9) | H9: =IF(OR(F9="",G9=""),"",F9/G9)
F10: =IF(OR(D10="",E10=""),"",D10/E10) | H10: =IF(OR(F10="",G10=""),"",F10/G10)
F11: =IF(OR(D11="",E11=""),"",D11/E11) | H11: =IF(OR(F11="",G11=""),"",F11/G11)
F12: =IF(OR(D12="",E12=""),"",D12/E12) | H12: =IF(OR(F12="",G12=""),"",F12/G12)
F13: =IF(OR(D13="",E13=""),"",D13/E13) | H13: =IF(OR(F13="",G13=""),"",F13/G13)
A15: BLADES
A16: Blade (name used in the dropdowns) | B16: Type | D16: Pack price (£) | E16: Blades per pack | F16: → Price per blade (£) | G16: Cuts per blade (est.) | H16: → Cost per cut (£) | I16: Notes / source
A17: Fine-point (Premium) | B17: Fine-point | D17: 9 | E17: 2 | F17: =IF(OR(D17="",E17=""),"",D17/E17) -> 4.5 | G17: 200 | H17: =IF(OR(F17="",G17=""),"",F17/G17) -> 0.0225 | I17: User, Oct 2026: £4.50 per blade from a 2-blade pack (pack price entered as £9.00). Cuts per blade: rough placeholder, real-world estimates 100–300. One 'cut' = one mat pass through the machine.
F18: =IF(OR(D18="",E18=""),"",D18/E18) | H18: =IF(OR(F18="",G18=""),"",F18/G18) | I18: Spare row — e.g. a deep-point blade.
F19: =IF(OR(D19="",E19=""),"",D19/E19) | H19: =IF(OR(F19="",G19=""),"",F19/G19)
F20: =IF(OR(D20="",E20=""),"",D20/E20) | H20: =IF(OR(F20="",G20=""),"",F20/G20)
A22: CRICUT JOBS — cost per A4 sheet cut
A23: Cricut job | B23: Mat used (dropdown) | C23: Blade used (dropdown) | D23: Sheets per mat load | E23: → Mat cost per use (£) | F23: → Blade cost per cut (£) | G23: → Cost per sheet (£) | H23: Used on | I23: Notes
A24: Main kiss-cut (sticker sheet, face up) | B24: StandardGrip 12x12 | C24: Fine-point (Premium) | D24: 1 | E24: =IF(B24="","",INDEX($H$6:$H$13,MATCH(B24,$A$6:$A$13,0))) -> 0.07037037 | F24: =IF(C24="","",INDEX($H$17:$H$20,MATCH(C24,$A$17:$A$20,0))) -> 0.0225 | G24: =IF(OR(E24="",F24="",D24=""),"",(E24+F24)/D24) -> 0.09287037 | H24: All three bin sticker tabs: 100x140 B29 (toggle B22); 202x140 & 280x200 B29 (toggle B22) | I24: Cuts the sticker outlines. v9: switched off (N) on the 100x140 tab per your v8 edit; still on (Y) for 202x140 and 280x200.
A25: Back cut (sticker sheet, face down) | B25: StandardGrip 12x24 | C25: Fine-point (Premium) | D25: 1 | E25: =IF(B25="","",INDEX($H$6:$H$13,MATCH(B25,$A$6:$A$13,0))) -> 0.26666667 | F25: =IF(C25="","",INDEX($H$17:$H$20,MATCH(C25,$A$17:$A$20,0))) -> 0.0225 | G25: =IF(OR(E25="",F25="",D25=""),"",(E25+F25)/D25) -> 0.28916667 | H25: 100x140 B31; 202x140 and 280x200 B31 | I25: Slit through the backing only, 15mm from the top edge. Uses the 12x24 mat (user, Oct 2026). If you fit two A4 sheets on one 12x24 mat, set Sheets per mat load to 2 and the cost per sheet halves.
A26: Wrap Print Then Cut (120gsm paper) | B26: StandardGrip 12x12 | C26: Fine-point (Premium) | D26: 1 | E26: =IF(B26="","",INDEX($H$6:$H$13,MATCH(B26,$A$6:$A$13,0))) -> 0.07037037 | F26: =IF(C26="","",INDEX($H$17:$H$20,MATCH(C26,$A$17:$A$20,0))) -> 0.0225 | G26: =IF(OR(E26="",F26="",D26=""),"",(E26+F26)/D26) -> 0.09287037 | H26: 100x140 B69 (toggle B68) | I26: Paper is often cut on a LightGrip mat — add one to the MATS table and switch this dropdown if you change.
A27: Peel marker sheet Print Then Cut | B27: StandardGrip 12x12 | C27: Fine-point (Premium) | D27: 1 | E27: =IF(B27="","",INDEX($H$6:$H$13,MATCH(B27,$A$6:$A$13,0))) -> 0.07037037 | F27: =IF(C27="","",INDEX($H$17:$H$20,MATCH(C27,$A$17:$A$20,0))) -> 0.0225 | G27: =IF(OR(E27="",F27="",D27=""),"",(E27+F27)/D27) -> 0.09287037 | H27: 100x140 B38 (shared by all sizes via B41) | I27: SmithPackaging label sheet, 35 marker sets per sheet.
E28: =IF(B28="","",INDEX($H$6:$H$13,MATCH(B28,$A$6:$A$13,0))) | F28: =IF(C28="","",INDEX($H$17:$H$20,MATCH(C28,$A$17:$A$20,0))) | G28: =IF(OR(E28="",F28="",D28=""),"",(E28+F28)/D28) | I28: Spare row — add a future job here, then link a product tab to its column G.
E29: =IF(B29="","",INDEX($H$6:$H$13,MATCH(B29,$A$6:$A$13,0))) | F29: =IF(C29="","",INDEX($H$17:$H$20,MATCH(C29,$A$17:$A$20,0))) | G29: =IF(OR(E29="",F29="",D29=""),"",(E29+F29)/D29)
E30: =IF(B30="","",INDEX($H$6:$H$13,MATCH(B30,$A$6:$A$13,0))) | F30: =IF(C30="","",INDEX($H$17:$H$20,MATCH(C30,$A$17:$A$20,0))) | G30: =IF(OR(E30="",F30="",D30=""),"",(E30+F30)/D30)
E31: =IF(B31="","",INDEX($H$6:$H$13,MATCH(B31,$A$6:$A$13,0))) | F31: =IF(C31="","",INDEX($H$17:$H$20,MATCH(C31,$A$17:$A$20,0))) | G31: =IF(OR(E31="",F31="",D31=""),"",(E31+F31)/D31)
A33: Cost per sheet = (mat cost per use + blade cost per cut) ÷ sheets per mat load. Lifespans are placeholders (no official Cricut data) — the back cut cost is especially sensitive to the 12x24 uses-per-mat figure.

Sheet Recurring Overhead
A1: Recurring Overhead — Subscriptions & Monthly Costs
A2: Blue = editable input. Black = calculated. Yellow = key assumption to review. Placeholder £0 values below — fill in once tools are actually chosen (design software/font licences, bookkeeping software — per chat, both are expected to be paid). Standing preference: search current UK pricing before finalising any of these, don't rely on training data.
A4: MONTHLY SUBSCRIPTIONS
A5: Item | B5: Cost (£/month) | C5: Category | D5: Notes | E5: full year
A6: Midjourney | B6: 8.9 | C6: Design | D6: Placeholder — not yet chosen (per chat, July 2026). Separate from Midjourney, already costed per-design-set in the Business Plan; add it here too if it becomes an ongoing monthly subscription. | E6: =B6*12 -> 106.8
A7: lovart | B7: 14.09 | C7: Design | D7: Placeholder — for any paid/commercial-use fonts beyond free/open-license options. | E7: =B7*12 -> 169.08
A8: Bookkeeping / accounting software | B8: 32.4 | C8: Admin | D8: Placeholder — decided to use paid software (per chat), specific tool not yet chosen. | E8: =B8*12 -> 388.8
A9: gmail account | B9: 7 | C9: Admin | D9: Entered by user (Sep 2026). | E9: =B9*12 -> 84
A10: Virtual office | B10: =E10/12 -> 20.833333 | C10: Admin | D10: Annual cost entered in column E (blue) and divided by 12 for the monthly figure. Entered by user; monthly figure added to the subtotal Sep 2026. | E10: 250
A11: Photoroom Pro (only if adopted) | B11: 0 | C11: Design | D11: Not yet adopted (Oct 2026). Free plan is unusable for eBay: every export is watermarked (breaches eBay Picture Policy) and commercial use is banned. Pro quoted at roughly £8/month (annual) to £11/month (monthly) by third-party sources — confirm on the UK checkout page before entering. Test eBay's free built-in background tool first. To add further subscriptions, insert rows above row 12 in Excel so the SUM range extends. | E11: =B11*12 -> 0
A12: MONTHLY OVERHEAD SUBTOTAL | B12: =SUM(B6:B11) -> 83.223333 | E12: =SUM(E6:E11) -> 998.68
A14: MONTHLY VOLUME SCENARIOS (pre-launch — no sales history yet)
A15: No orders yet, so these are three structured estimates rather than one guess: a comparable/benchmark figure, a target anchored to your own break-even goal, and a production-capacity ceiling — a bottom-up/top-down/proxy approach commonly recommended for pre-launch forecasting (source: Glencoyne, 'Sales Forecasting Without Historical Data', 2025). Comparable figures below from salesdoe.com's analysis of 797 Etsy shops (2025), Etsy Community Forum seller reports, and TechPenny 'When To Expect First Sale On Etsy' (2023) — accessed July 2026.
A17: Scenario | B17: Monthly Volume (stickers) | C17: Basis | D17: Notes / Source
A18: Conservative | B18: 10 | C18: New-shop comparable benchmark | D18: Seller community reports commonly cite roughly 3–10 sales in a new shop's first month; a study of 797 Etsy shops found ~16 sales/month typical for a 'middling' shop after a full year. 10/month is a placeholder mid-point — edit if you have a firmer view.
A19: Base / Target | B19: 40 | C19: Anchored to your own break-even goal | D19: Placeholder target. Business Plan Section 9 is under revision — break-even is being rebuilt from this workbook (see the Break-Even Calculator on the Tier 1 sheet).
A20: Optimistic / Capacity ceiling | B20: =B23 -> 115.46667 | C20: Production capacity, not demand | D20: What you COULD produce, not necessarily what you will sell — see the capacity calculation just below. Treat as an upper bound, not a forecast.
A22: Hours/week available for production (your input) | B22: 1 | D22: Not yet known — set this to see your realistic capacity ceiling. Left at 0 as a placeholder.
A23: → Capacity-based monthly volume (stickers) | B23: =IFERROR(B22*4.33/(45/60)*20,0) -> 115.46667 | D23: Hours/week × 4.33 weeks/month ÷ (45 min ÷ 60) × 20 stickers/batch, using the faster end of the 45–70 min/20-sticker batch estimate in Business Plan Section 10 (production workflow) — the manual trim/round/nick cutting steps for bin stickers haven’t been timed at real volume yet, so treat this as optimistic.
A25: OVERHEAD COST PER STICKER BY SCENARIO
A26: Scenario | B26: Overhead Cost / Sticker (£)
A27: Conservative | B27: =IFERROR($B$12/B18,0) -> 8.3223333
A28: Base / Target | B28: =IFERROR($B$12/B19,0) -> 2.0805833
A29: Optimistic / Capacity ceiling | B29: =IFERROR($B$12/B20,0) -> 0.72075635
A31: ACTIVE SCENARIO (used in Bin Stickers sheet & Break-Even Calculator)
A32: Active scenario | B32: Conservative | D32: Dropdown — pick Conservative, Base / Target, or Optimistic / Capacity ceiling. Defaults to Conservative: pricing against the low estimate means you stay covered even if early volume is slow; switch it once you have a few months of real data.
A33: → Active monthly volume (stickers) | B33: =INDEX(B18:B20,MATCH(B32,A18:A20,0)) -> 10
A34: → Active overhead cost per sticker (£) | B34: =IFERROR($B$12/B33,0) -> 8.3223333

Sheet cost per item
A1: item | B1: count | C1: cost | D1: shipping | E1: total per item | I1: total | J1: count | K1: total | L1: per item | M1: diff
A2: Stickiply | I2: Stickiply
A3: white vinyl | B3: 10 | C3: 6.5 | E3: =C3/B3 -> 0.65 | I3: white vinyl | J3: 25 | K3: =C4+C14 -> 25.9 | L3: =K3/J3 -> 1.036
A4: white vinyl | B4: 25 | C4: 13.25 | E4: =C4/B4 -> 0.53 | I4: white vinyl | J4: 50 | K4: =C5+C15 -> 46.15 | L4: =K4/J4 -> 0.923 | M4: =L3-L4 -> 0.113
A5: white vinyl | B5: 50 | C5: 22.5 | E5: =C5/B5 -> 0.45 | I5: white vinyl | J5: 100 | K5: =C6+C16 -> 87 | L5: =K5/J5 -> 0.87 | M5: =L4-L5 -> 0.053
A6: white vinyl | B6: 100 | C6: 43 | E6: =C6/B6 -> 0.43 | I6: white vinyl | J6: 200 | K6: =C7+C17 -> 165.5 | L6: =K6/J6 -> 0.8275 | M6: =L5-L6 -> 0.0425
A7: white vinyl | B7: 200 | C7: 80 | E7: =C7/B7 -> 0.4 | I7: white vinyl | J7: 500 | K7: =C8+C18 -> 384 | L7: =K7/J7 -> 0.768 | M7: =L6-L7 -> 0.0595
A8: white vinyl | B8: 500 | C8: 175 | E8: =C8/B8 -> 0.35 | I8: clear vinyl | J8: 25 | K8: =C10+C14 -> 28.9 | L8: =K8/J8 -> 1.156 | M8: =L7-L8 -> -0.388
A9: clear vinyl | B9: 10 | C9: 7.5 | E9: =C9/B9 -> 0.75 | I9: clear vinyl | J9: 50 | K9: =C11+C15 -> 51.15 | L9: =K9/J9 -> 1.023 | M9: =L8-L9 -> 0.133
B10: 25 | C10: 16.25 | E10: =C10/B10 -> 0.65 | I10: clear vinyl | J10: 100 | K10: =C12+C16 -> 92 | L10: =K10/J10 -> 0.92 | M10: =L9-L10 -> 0.103
B11: 50 | C11: 27.5 | E11: =C11/B11 -> 0.55 | I11: clear vinyl | J11: 200 | K11: =2*C12+C17 -> 181.5 | L11: =K11/J11 -> 0.9075 | M11: =L10-L11 -> 0.0125
B12: 100 | C12: 48 | E12: =C12/B12 -> 0.48 | I12: clear vinyl | J12: 500 | K12: =5*C12+C18 -> 449 | L12: =K12/J12 -> 0.898 | M12: =L11-L12 -> 0.0095
A13: lamination | B13: 10 | C13: 5.5 | E13: =C13/B13 -> 0.55 | I13: Cricut | J13: 20 | K13: =C20+C22 -> 13 | L13: =K13/J13 -> 0.65
B14: 25 | C14: 12.65 | E14: =C14/B14 -> 0.506 | I14: Cricut | J14: 60 | K14: =K13*3 -> 39 | L14: =K14/J14 -> 0.65
B15: 50 | C15: 23.65 | E15: =C15/B15 -> 0.473 | I15: Cricut | J15: 100 | K15: =K13*5 -> 65 | L15: =K15/J15 -> 0.65
B16: 100 | C16: 44 | E16: =C16/B16 -> 0.44
B17: 200 | C17: 85.5 | E17: =C17/B17 -> 0.4275
B18: 500 | C18: 209 | E18: =C18/B18 -> 0.418
A19: Cricut
A20: white vinyl | B20: 20 | C20: 6.5 | E20: =C20/B20 -> 0.325
A21: clear vinyl | B21: 20 | C21: 6.5 | E21: =C21/B21 -> 0.325
A22: lamination | B22: 20 | C22: 6.5 | E22: =C22/B22 -> 0.325

Sheet Ebay costs
A1: EBAY MARKETING — PROMOTED LISTINGS & FEE STACK (added Aug 2026)
A2: Ad spend is a VARIABLE cost (scales with price × volume), unlike the fixed monthly subscriptions above — deliberately kept as its own block rather than folded into the MONTHLY OVERHEAD SUBTOTAL (B11), since mixing a %-of-price cost into that flat per-sticker allocation would distort it whenever price changes. See chat for full research: ad-rate benchmarks, eBay's own suggested rates vs independent guidance, and how this stacks with Final Value Fee / per-order fee / regulatory fee. FLAG: price input below (£3.00) is a placeholder mid-point of the user-specified £2-4 'simple stickers' range (Aug 2026 chat) — this differs from the Business Plan Section 3 bin sticker range (£5-8/set) and the 'Bin Stickers 100x140 4pk' sheet (~£6/pack). Clarify whether this is a new single-sticker product tier or a per-unit breakdown of the existing set price, then reconcile across files.
A4: Item | B4: Value | C4: Notes
A5: Assumed sale price per unit (£) | B5: 5 | C5: £5.00 per 4-pack set by user (Oct 2026), Letter postage (£0.91), small size only. Previously £4.00 (Sep 2026) — at £4.00 profit was about £0.08 a pack before overhead. Competitor four-pack band is £1.69-£1.99 on eBay — see Competitor-Research.md. Medium and Large prices to be set separately.
A6: Promoted Listings ad rate (% of sale price) | B6: 0.04 | C6: User-selected 4% (Aug 2026 chat) — independent-guidance recommended ceiling for small/new sellers. eBay's own suggested rate typically runs 8-15% and is optimised for eBay's revenue, not yours; community reports of 2-30% exist depending on category/margin. General/Standard campaign (cost-per-sale) assumed, not Priority/Advanced (cost-per-click) — right choice for a single-product launch at this volume.
A7: eBay Final Value Fee (business seller, standard category) | B7: 0.128 | C7: 12.8% of item price + postage, most categories, checked Aug 2026. Matches the ~13% already assumed in Business Plan Section 6, just broken out precisely here.
A8: eBay per-order fee (£, flat) | B8: 0.3 | C8: 30p per order under £10; rises to 40p for orders ≥£10 (changed Feb 2026 — NOT yet reflected in Business Plan Section 6 or the 4pk cost sheet, worth adding there too). At a £2-4 unit price this stays at 30p unless bundling pushes a single order over £10.
A9: eBay Regulatory Operating Fee (% of item price + postage) | B9: 0.004 | C9: ~0.35-0.43% UK regulatory fee, introduced April 2024, applies to all UK business sellers regardless of ad usage — also not currently broken out elsewhere in the workbook. 0.4% used as a midpoint.
A10: eBay UK VAT on seller fees (20%, non-recoverable — not VAT-registered) | B10: 0.2 | C10: eBay UK charges 20% VAT on top of all business-seller fees (Final Value Fee, per-order fee, Regulatory Operating Fee, Promoted Listings ad fee). Not VAT-registered, so this is a real unreclaimable cost added to the fee stack. Single input cell — all fee formulas below reference this.
A11: → COST PER UNIT SOLD
A12: Ad spend per unit (£) | B12: =B6*B5*(1+$B$10) -> 0.24
A13: Final Value Fee per unit (£) | B13: =B7*B5*(1+$B$10) -> 0.768
A14: Regulatory fee per unit (£) | B14: =B9*B5*(1+$B$10) -> 0.024
A15: TOTAL EBAY PLATFORM COST PER UNIT (FVF + per-order + regulatory + ad) (£) | B15: =SUM(B12:B14)+B8*(1+$B$10) -> 1.392
A16: Net proceeds per unit after all eBay fees (£) | B16: =B5-B15 -> 3.608
A17: Total eBay fees as % of sale price | B17: =B15/B5 -> 0.2784
A19: → MONTHLY, AT ACTIVE SCENARIO VOLUME (from ACTIVE SCENARIO block above)
A20: Active monthly volume (stickers) | B20: ='Recurring Overhead'!B33 -> 10
A21: Monthly ad spend at active volume (£) | B21: =B12*B20 -> 2.4
A22: Monthly TOTAL eBay platform fees at active volume (£) | B22: =B15*B20 -> 13.92
A24: Fees are per-sale variable costs, deliberately NOT part of the fixed 'Recurring Overhead' sheet. They feed the Break-Even Calculator on the Tier 1 sheet.
A26: → PRICE SENSITIVITY — same fee stack at other sale prices
A27: Item | B27: Sale price (£) | C27: Total eBay fees (£) | D27: Net proceeds (£) | E27: Fees as % of price
A28: Price point 1 | B28: 3 | C28: =(B28*($B$6+$B$7+$B$9)+$B$8)*(1+$B$10) -> 0.9792 | D28: =B28-C28 -> 2.0208 | E28: =C28/B28 -> 0.3264
A29: Price point 2 | B29: 4 | C29: =(B29*($B$6+$B$7+$B$9)+$B$8)*(1+$B$10) -> 1.1856 | D29: =B29-C29 -> 2.8144 | E29: =C29/B29 -> 0.2964
A30: Price point 3 | B30: 5 | C30: =(B30*($B$6+$B$7+$B$9)+$B$8)*(1+$B$10) -> 1.392 | D30: =B30-C30 -> 3.608 | E30: =C30/B30 -> 0.2784
A31: Price point 4 | B31: 6 | C31: =(B31*($B$6+$B$7+$B$9)+$B$8)*(1+$B$10) -> 1.5984 | D31: =B31-C31 -> 4.4016 | E31: =C31/B31 -> 0.2664

Sheet Etsy
A1: Etsy — Fees & Advertising (UK shop, not VAT-registered)
A2: Blue = editable input. Black = calculated. Companion to Etsy-Marketing-Guide.md — see that file for full context/sources. FLAG: price input below (£3.00) is a placeholder mid-point of the user-specified £2-4 'simple stickers' range — differs from Business Plan Section 3 (£5-8/set bin stickers). 'Sale price' here is treated as the TOTAL amount the buyer pays (item + any shipping charged), matching how Etsy calculates its fees.
A4: INPUTS
A5: Item | B5: Value | C5: Notes
A6: Assumed sale price per unit, total incl. shipping (£) | B6: 3 | C6: Placeholder — see flag above. Edit once price is locked.
A7: Listing fee per listing (£) | B7: 0.16 | C7: ~$0.20 USD converted. Charged whether or not it sells; renews every 4 months and again per sale on multi-quantity listings — this model assumes 1 listing fee per unit sold, the conservative case.
A8: Transaction fee rate | B8: 0.065 | C8: 6.5% of item price + shipping + gift wrap.
A9: Payment processing rate | B9: 0.04 | C9: 4% + fixed fee below. Etsy Payments is mandatory, no alternative processor option.
A10: Payment processing fixed fee (£) | B10: 0.2
A11: Regulatory Operating Fee rate | B11: 0.0032 | C11: 0.32% of item price + shipping, UK-specific since 2022.
A12: VAT on Etsy fees (applies — not VAT-registered) | B12: 0.2 | C12: 20% VAT charged on ALL of Etsy's fees above when the seller isn't VAT-registered (per current business plan strategy). Set to 0% here if VAT registration status changes.
A13: Offsite Ads currently active? (Y/N) | B13: N | C13: Optional and should be switched OFF in Shop Manager while trailing 12-month revenue is under $10,000 USD (~£8,000) — see guide. Becomes mandatory (can't be set to N) once that threshold is crossed.
A14: Offsite Ads fee rate (if active) | B14: 0.15 | C14: 15% below $10k trailing revenue, 12% once mandatory at/above it.
A15: Etsy Ads (onsite) daily budget (£) — optional, separate CPC spend | B15: 1 | C15: Minimum ~£1/day. This is a controllable CPC budget, NOT a %-of-sale fee — kept separate from the cost-per-unit maths below since it doesn't scale with units sold. Shown as a monthly figure further down.
A17: → COST PER UNIT SOLD (Listing + Transaction + Payment processing + Regulatory + VAT-on-fees)
A18: Transaction fee (£) | B18: =B8*B6 -> 0.195
A19: Payment processing fee (£) | B19: =B9*B6+B10 -> 0.32
A20: Regulatory fee (£) | B20: =B11*B6 -> 0.0096
A21: Subtotal before VAT (£) | B21: =B7+B18+B19+B20 -> 0.6846
A22: VAT on fees (£) | B22: =B21*B12 -> 0.13692
A23: Offsite Ads fee incl. its own VAT (£), if active | B23: =IF(B13="Y",B14*B6*(1+B12),0) -> 0
A24: TOTAL ETSY FEES PER UNIT (£) | B24: =B21+B22+B23 -> 0.82152
A25: Net proceeds per unit after all Etsy fees (£) | B25: =B6-B24 -> 2.17848
A26: Total Etsy fees as % of sale price | B26: =B24/B6 -> 0.27384
A28: → MONTHLY, AT ACTIVE SCENARIO VOLUME (from 'Recurring Overhead' sheet)
A29: Active monthly volume (stickers) | B29: ='Recurring Overhead'!B33 -> 10
A30: Monthly total Etsy fees at active volume (£) | B30: =B24*B29 -> 8.2152
A31: Monthly Etsy Ads (onsite) budget, if used (£) | B31: =B15*30 -> 30 | C31: Independent of units sold — a controllable CPC budget, not charged per unit.
A33: Not wired into the 'Recurring Overhead' sheet's fixed subscription subtotal (B11), same rationale as the eBay block there: these are %-of-price/variable costs, and mixing them into a flat £/sticker overhead figure would distort it whenever price changes. See Etsy-Marketing-Guide.md for the recommended launch approach (Offsite Ads off, small onsite Ads budget, fix listing fundamentals first).

Sheet Amazon
A1: Amazon — Fees & Advertising (UK, FBM assumed)
A2: Blue = editable input. Black = calculated. Companion to Amazon-Marketing-Guide.md. FLAG: same £2-4 vs £5-8 price ambiguity as the other sheets applies here — £3.00 used as a placeholder. Amazon Handmade eligibility (12.24% flat referral fee, vs standard 8-15% category fee) is NOT confirmed for laminated vinyl stickers — standard referral fee used below as the conservative default; switch the input if Handmade is confirmed eligible.
A4: INPUTS
A5: Item | B5: Value | C5: Notes
A6: Assumed sale price per unit (£) | B6: 3 | C6: Placeholder — see flag above.
A7: Referral fee rate | B7: 0.15 | C7: 8-15% typical range by category; 15% (top of range) used as the conservative default. Confirm actual category rate before launch — check Amazon Handmade (12.24% flat) eligibility too.
A8: Minimum referral fee (£) | B8: 0.25 | C8: Applies regardless of price — matters at £2-4 unit prices since the percentage-based fee may fall below this floor.
A9: Digital Services Tax pass-through rate | B9: 0.02 | C9: Applied on top of the referral fee for UK-established sellers.
A10: Using Professional account? (Y/N) | B10: N | C10: Required for Sponsored Products (PPC) access, Buy Box eligibility, and new listing creation. Guide recommends holding off until volume/margin justify the flat monthly cost. Set to 'Y' once committed.
A11: Professional account monthly fee (£) | B11: 25
A12: Individual account per-item fee (£, if not Professional) | B12: 0.75
A13: Sponsored Products target ACoS (launch phase) | B13: 0.35 | C13: 30-40%+ is normal/accepted during a launch phase per general guidance; established-product benchmarks run 15-25%. Only relevant if Professional account + Sponsored Products are actually turned on.
A15: → COST PER UNIT SOLD (selling fees only, before advertising)
A16: Referral fee, greater of rate or minimum (£) | B16: =MAX(B7*B6,B8) -> 0.45
A17: Referral fee incl. DST pass-through (£) | B17: =B16*(1+B9) -> 0.459
A18: Account fee per unit — Individual only (£) | B18: =IF(B10="Y",0,B12) -> 0.75 | C18: Professional's £25/mo is a flat monthly cost, not per-unit — shown separately below.
A19: TOTAL SELLING FEES PER UNIT (£) | B19: =B17+B18 -> 1.209
A20: Net proceeds per unit after selling fees, before advertising (£) | B20: =B6-B19 -> 1.791
A21: Total selling fees as % of sale price | B21: =B19/B6 -> 0.403
A23: → MONTHLY, AT ACTIVE SCENARIO VOLUME
A24: Active monthly volume (stickers) | B24: ='Recurring Overhead'!B33 -> 10
A25: Monthly total selling fees at active volume (£) | B25: =B19*B24 -> 12.09
A26: Monthly Professional account fee, if used (£) | B26: =IF(B10="Y",B11,0) -> 0
A27: Estimated monthly Sponsored Products spend, if Professional + advertising used (£) | B27: =IF(B10="Y",B13*B6*B24,0) -> 0 | C27: Approximation: ACoS × assumed monthly revenue, treating all volume as ad-attributed — a simplification, real ad-attributed revenue will be a subset of total sales. CPC spend is NOT cost-per-sale, so this is charged whether or not those specific clicks convert.
A29: Not wired into the 'Recurring Overhead' sheet's fixed subscription subtotal (B11) — same rationale as the eBay and Etsy blocks: variable/%-of-price costs kept separate from the flat £/sticker overhead allocation. Guide recommends holding Professional account + Sponsored Products off until Amazon volume and margin are established via eBay/Etsy first — the Y/N toggles above default to 'off' accordingly.

Sheet Merge notes
A1: Merge notes — StickerBinStickersCosts_v5 (Oct 2026; v4 notes below)
A2: Source versions reviewed
A3: StickerBinStickersCosts.xlsx (31 Jul) and _v2_old (2 Aug): nothing unique — fully superseded.
A4: _v3 (13 Sep): base of this file. Only version with the Medium and Large sheets.
A5: _v2 (20 Sep, newest edits): Recurring Overhead layout (gmail, virtual office), user decisions on baseline inputs.
A6: Decisions by user
A7: Vinyl £0.325, laminate £0.325, ink £0.10 (sticker and card). Address labels: SmithPackaging. Overhead list from v2. Scratch block deleted (Joy Xtra £180, lamp, bin, tools, file holder, Avery row, Cricut-vs-Stickiply cells).
A8: Fixes applied
A9: Cost per label used a hardcoded /3; now divides by labels per sheet (B55).
A10: Optimistic overhead scenario pointed at hours/week; now uses capacity volume.
A11: Virtual office (£250/yr) now in monthly overhead as £250/12; 'full year' column now x12 for Midjourney and lovart (was x6).
A12: Explore 5 = £330 (Ultimate Bundle) in the core subtotal; laminator = Stickiply £115; corner punch, Slice and mat moved to an On-hold group.
... A70: No profit figures change: every tab's selected tier is unchanged (Small = Letter £0.91), and Tracked services are not offered at launch. Letter (£0.91) and Large Letter (£1.55) prices did not change on 5 Oct 2026.
